{
    "title": "Dr.STONE SCIENCE FUTURE Cour 3",
    "slug": "dr-dotstone-science-future-cour-3",
    "description": "Third part of Dr. Stone: Science Future.",
    "genres": [
        "Adventure",
        "Comedy"
    ],
    "studio": "TMS Entertainment",
    "cover_image": "https://i.animepahe.pw/posters/3aa251d240623be60f71a96dc593d38354a6a29d6653b4864784668edab359ac.jpg",
    "background_image": "https://i.animepahe.pw/covers/cover_default3.jpg",
    "release_date": "2026-01-01",
    "status": "ongoing",
    "total_episodes": 9,
    "episodes": [
        {
            "episode_number": 25,
            "resolutions": {
                "360p": "https://kwik.cx/e/lqa9pZWj62HL",
                "720p": "https://kwik.cx/e/jecsMHx7PeJ6",
                "1080p": "https://kwik.cx/e/FHwZR5Fgyqkb"
            }
        },
        {
            "episode_number": 26,
            "resolutions": {
                "360p": "https://kwik.cx/e/VsgnKtSzyFSN",
                "720p": "https://kwik.cx/e/35L2zJvuXXBN",
                "1080p": "https://kwik.cx/e/6urioHlVwd5x"
            }
        },
        {
            "episode_number": 27,
            "resolutions": {
                "360p": "https://kwik.cx/e/OwWkujYBteFo",
                "720p": "https://kwik.cx/e/JzRXRc6WKsz7",
                "1080p": "https://kwik.cx/e/7EJ5DTj1lrdj"
            }
        },
        {
            "episode_number": 28,
            "resolutions": {
                "360p": "https://kwik.cx/e/VrdzoqN0O7bJ",
                "720p": "https://kwik.cx/e/dGe2v6dZtqjF",
                "1080p": "https://kwik.cx/e/h335AveBWSt7"
            }
        },
        {
            "episode_number": 29,
            "resolutions": {
                "360p": "https://kwik.cx/e/PmaxOlJdaF8U",
                "720p": "https://kwik.cx/e/SJ28RysGncUL",
                "1080p": "https://kwik.cx/e/GrKOKpVKwPfv"
            }
        },
        {
            "episode_number": 30,
            "resolutions": {
                "360p": "https://kwik.cx/e/K7LfAUriSaVP",
                "720p": "https://kwik.cx/e/2B0F7dC7Qwwn",
                "1080p": "https://kwik.cx/e/FKxvHtXDYfhY"
            }
        },
        {
            "episode_number": 31,
            "resolutions": {
                "360p": "https://kwik.cx/e/mRYVraLHSRO4",
                "720p": "https://kwik.cx/e/79mGPfNS6qSz",
                "1080p": "https://kwik.cx/e/zOhjtPdnhwnA"
            }
        },
        {
            "episode_number": 32,
            "resolutions": {
                "360p": "https://kwik.cx/e/oyLsm4f1MTdq",
                "720p": "https://kwik.cx/e/z3tiV66ovtbz",
                "1080p": "https://kwik.cx/e/z202F08GbC6y"
            }
        },
        {
            "episode_number": 33,
            "resolutions": {
                "360p": "https://kwik.cx/e/uvHiG1HGKM24",
                "720p": "https://kwik.cx/e/S4rjXqqxkiDp",
                "1080p": "https://kwik.cx/e/0K4lerO3H9VY"
            }
        }
    ]
}