{
    "title": "Ichijyoma Mankitsu Gurashi!",
    "slug": "ichijyoma-mankitsu-gurashi-one",
    "description": "Meiko, a country girl, enrolls in a prestigious all-girls school under the condition that she joins a volunteer program. But instead of a typical school service, she finds herself living and working at a manga cafe!Surprisingly, life in a cramped booth isn't so bad\u2014and with a staff full of cute high school girls, it might even be fun!Come enjoy the charm of a manga cafe filled with high school girls!",
    "genres": [
        "Comedy",
        "Ecchi"
    ],
    "studio": "PRA",
    "cover_image": "https://i.animepahe.pw/posters/f824a266857028e9fa749d2671dde8885d7542cc1414323972d8298e7690e446.jpg",
    "background_image": "https://i.animepahe.pw/covers/cover_default3.jpg",
    "release_date": "2026-01-01",
    "status": "ongoing",
    "total_episodes": 7,
    "episodes": [
        {
            "episode_number": 1,
            "resolutions": {
                "360p": "https://kwik.cx/e/nXMt38AJ2xqP",
                "720p": "https://kwik.cx/e/bKB7gCO4MYbu",
                "1080p": "https://kwik.cx/e/PBylNUw8siet"
            }
        },
        {
            "episode_number": 2,
            "resolutions": {
                "360p": "https://kwik.cx/e/DbmS1wltcr2k",
                "720p": "https://kwik.cx/e/YCSXfL1MKRTX",
                "1080p": "https://kwik.cx/e/NSzoSNNXhovm"
            }
        },
        {
            "episode_number": 3,
            "resolutions": {
                "360p": "https://kwik.cx/e/pLbErdqJsDmD",
                "720p": "https://kwik.cx/e/cy4LrqTtx6eJ",
                "1080p": "https://kwik.cx/e/YPExVoqVvRHV"
            }
        },
        {
            "episode_number": 4,
            "resolutions": {
                "360p": "https://kwik.cx/e/AKeYOaAngbgS",
                "720p": "https://kwik.cx/e/TZ2cbrxThQlc",
                "1080p": "https://kwik.cx/e/1PNijbltJPLu"
            }
        },
        {
            "episode_number": 5,
            "resolutions": {
                "360p": "https://kwik.cx/e/FT69ov0HaOEe",
                "720p": "https://kwik.cx/e/MfLYTpJDyLBa",
                "1080p": "https://kwik.cx/e/sFSyb5rUVH3z"
            }
        },
        {
            "episode_number": 6,
            "resolutions": {
                "360p": "https://kwik.cx/e/OgIKcHCZYBxb",
                "720p": "https://kwik.cx/e/ZC2vpVE3TxzW",
                "1080p": "https://kwik.cx/e/0TcT5ee16hU1"
            }
        },
        {
            "episode_number": 7,
            "resolutions": {
                "360p": "https://kwik.cx/e/A2aGY50oLrEj",
                "720p": "https://kwik.cx/e/YxH67jPqS1M2",
                "1080p": "https://kwik.cx/e/OK6MQrqc0pQR"
            }
        }
    ]
}