{
    "title": "Rail Romanesque",
    "slug": "rail-romanesque",
    "description": "The year is 1989. After the nation of Hinomoto was destabilized during the past World War, the rise of new technologies has enabled its revitalization. Modern engineering has given birth to aircraft, gasoline engines, and geomagnetic technology\u2014revolutionizing transportation. Railroads have been rendered nearly obsolete and replaced by more efficient modes of transit.However, a group of lively \"Raillords\" aims to renew the railroads' former glory. The Raillords, personified as energetic and spirited girls, act as humanoid control modules for their assigned railways. They meet in Ohitoyo City for the Raillord Summit, headed by Suzushiro, a Raillord from Manoka Railways. Together, the group capitalizes on its teamwork to get the railroads back on track, ushering in a \"new railroad age.\"",
    "genres": [
        "Slice of Life"
    ],
    "studio": "Saetta",
    "cover_image": "https://i.animepahe.pw/posters/e5bf95b756e446946c6e64f33aef75972f753fe7769b9b0a9986779f95b2820e.jpg",
    "background_image": "https://i.animepahe.pw/covers/cover_default0.jpg",
    "release_date": "2020-01-01",
    "status": "completed",
    "total_episodes": 12,
    "episodes": [
        {
            "episode_number": 1,
            "resolutions": {
                "360p": "https://kwik.cx/e/ecNLt8koMFa7",
                "720p": "https://kwik.cx/e/X2ggClVPU98j",
                "1080p": "https://kwik.cx/e/TVU9SSvikKgY"
            }
        },
        {
            "episode_number": 2,
            "resolutions": {
                "360p": "https://kwik.cx/e/XJOKAmzLGUZr",
                "720p": "https://kwik.cx/e/luDn0VJNntls",
                "1080p": "https://kwik.cx/e/Yr7XKZ2dTJue"
            }
        },
        {
            "episode_number": 3,
            "resolutions": {
                "360p": "https://kwik.cx/e/M5casBMQz1WZ",
                "720p": "https://kwik.cx/e/36jJUFmofWrK",
                "1080p": "https://kwik.cx/e/PorU20gP9kdy"
            }
        },
        {
            "episode_number": 4,
            "resolutions": {
                "360p": "https://kwik.cx/e/faXBNMNwecOL",
                "720p": "https://kwik.cx/e/YEJ7KtSw7uPP",
                "1080p": "https://kwik.cx/e/mjXUHcXS4u2w"
            }
        },
        {
            "episode_number": 5,
            "resolutions": {
                "360p": "https://kwik.cx/e/OHMbrfeqWf39",
                "720p": "https://kwik.cx/e/nM3mVoqvAf7A",
                "1080p": "https://kwik.cx/e/tR7oKnWK2EtI"
            }
        },
        {
            "episode_number": 6,
            "resolutions": {
                "360p": "https://kwik.cx/e/zDLDBxN3I5kf",
                "720p": "https://kwik.cx/e/4ThAGgqIOrQX",
                "1080p": "https://kwik.cx/e/9u17HHmFjkzQ"
            }
        },
        {
            "episode_number": 7,
            "resolutions": {
                "360p": "https://kwik.cx/e/GT5v90YvsEXI",
                "720p": "https://kwik.cx/e/LFv7NbfPSS9d",
                "1080p": "https://kwik.cx/e/tXUZwPh7ovmG"
            }
        },
        {
            "episode_number": 8,
            "resolutions": {
                "360p": "https://kwik.cx/e/3sA042pCSyxV",
                "720p": "https://kwik.cx/e/I8EZF12hRCGR",
                "1080p": "https://kwik.cx/e/UdQQq3APPAAN"
            }
        },
        {
            "episode_number": 9,
            "resolutions": {
                "360p": "https://kwik.cx/e/MCa4KTDetIxV",
                "720p": "https://kwik.cx/e/CkkC9GBYJM8N",
                "1080p": "https://kwik.cx/e/p4Evjlp100dF"
            }
        },
        {
            "episode_number": 10,
            "resolutions": {
                "360p": "https://kwik.cx/e/bSilEANptM21",
                "720p": "https://kwik.cx/e/GeUCOInKPnLo",
                "1080p": "https://kwik.cx/e/NCZw8SzUqs3t"
            }
        },
        {
            "episode_number": 11,
            "resolutions": {
                "360p": "https://kwik.cx/e/ScnAbiIMTF3s",
                "720p": "https://kwik.cx/e/ryOt8iC4XMMp",
                "1080p": "https://kwik.cx/e/fu0ktCCKHMs8"
            }
        },
        {
            "episode_number": 12,
            "resolutions": {
                "360p": "https://kwik.cx/e/efpVNcGSvRPC",
                "720p": "https://kwik.cx/e/IF7k85hCcsRA",
                "1080p": "https://kwik.cx/e/Wp83lS5XdH2b"
            }
        }
    ]
}